jettquant/__about__.py
jettquant/__init__.py
jettquant/constants.py
jettquant/radar_engine.py
jettquant/event/__init__.py
jettquant/event/event_engine.py
jettquant/event/event_type.py
jettquant-1.2.1.dist-info/METADATA
jettquant-1.2.1.dist-info/WHEEL
jettquant-1.2.1.dist-info/licenses/LICENSE.txt
jettquant-1.2.1.dist-info/RECORD
