Metadata-Version: 2.4
Name: jettquant
Version: 1.2.1
Summary: Personal quantification tool
Project-URL: Homepage, https://github.com/jett2025ab/jettquant
Project-URL: Repository, https://github.com/jett2025ab/jettquant
Project-URL: Documentation, https://github.com/jett2025ab/jettquant#readme
Author-email: jett <jett2025ab@outlook.com>
License-Expression: MIT
License-File: LICENSE.txt
Keywords: finance,market,quant,trading
Classifier: License :: OSI Approved :: MIT License
Classifier: Programming Language :: Python
Classifier: Programming Language :: Python :: 3.10
Classifier: Programming Language :: Python :: 3.11
Classifier: Programming Language :: Python :: 3.12
Classifier: Topic :: Office/Business :: Financial
Requires-Python: <3.13,>=3.10
Requires-Dist: pandas
Requires-Dist: xtquant
Provides-Extra: test
Requires-Dist: pytest; extra == 'test'
Requires-Dist: pytest-cov; extra == 'test'
